CIMLA/CIMLA.py
CIMLA/ConfigParser.py
CIMLA/Dataset.py
CIMLA/PostProcessor.py
CIMLA/__init__.py
CIMLA/defaults.py
CIMLA/main.py
CIMLA/utils.py
CIMLA/ML/BaseModels.py
CIMLA/ML/Classification.py
CIMLA/ML/Regression.py
CIMLA/ML/__init__.py
CIMLA/ML/archs/MLP.py
CIMLA/ML/archs/__init__.py
CIMLA/attribution/BaseModels.py
CIMLA/attribution/SHAP.py
CIMLA/attribution/__init__.py
CIMLA/attribution/metrics.py
CIMLA-0.0.18.dist-info/LICENSE
CIMLA-0.0.18.dist-info/METADATA
CIMLA-0.0.18.dist-info/WHEEL
CIMLA-0.0.18.dist-info/entry_points.txt
CIMLA-0.0.18.dist-info/top_level.txt
CIMLA-0.0.18.dist-info/RECORD
